{"stats":{"minecraft:dropped":{"minecraft:stick":2,"minecraft:conduit":1280,"minecraft:white_concrete":1},"minecraft:mined":{"minecraft:grass_block":4},"minecraft:used":{"minecraft:oak_trapdoor":2,"minecraft:water_bucket":5,"minecraft:orange_concrete_powder":306,"minecraft:jungle_leaves":37,"minecraft:end_rod":90,"minecraft:cobblestone_stairs":33,"minecraft:dropper":8,"minecraft:orange_concrete":155,"minecraft:birch_leaves":33,"minecraft:birch_planks":36,"minecraft:red_stained_glass":2,"minecraft:stripped_birch_log":28,"minecraft:red_sandstone_slab":87,"minecraft:dispenser":6,"minecraft:redstone":79,"minecraft:jungle_fence":3,"minecraft:white_concrete_powder":2,"minecraft:white_terracotta":4,"minecraft:brown_concrete":2,"minecraft:stone":142,"minecraft:redstone_block":9,"minecraft:white_shulker_box":3,"minecraft:quartz_stairs":358,"minecraft:cobblestone_slab":134,"minecraft:gold_ore":9,"minecraft:spruce_leaves":4,"minecraft:oak_leaves":120,"minecraft:orange_stained_glass":2,"minecraft:torch":20,"minecraft:jungle_wood":13,"minecraft:mossy_cobblestone":13,"minecraft:dirt":44,"minecraft:lime_terracotta":6,"minecraft:comparator":10,"minecraft:vine":15,"minecraft:dark_prismarine_slab":61,"minecraft:oak_slab":11,"minecraft:hopper":1,"minecraft:orange_glazed_terracotta":4,"minecraft:cobblestone_wall":147,"minecraft:yellow_stained_glass_pane":1,"minecraft:jungle_slab":5,"minecraft:yellow_concrete":209,"minecraft:oak_wood":69,"minecraft:pink_terracotta":44,"minecraft:chiseled_quartz_block":23,"minecraft:lingering_potion":72,"minecraft:jungle_trapdoor":11,"minecraft:black_concrete_powder":33,"minecraft:nether_brick_stairs":5,"minecraft:birch_fence":260,"minecraft:redstone_torch":15,"minecraft:red_sandstone_stairs":27,"minecraft:sticky_piston":7,"minecraft:piston":3,"minecraft:packed_ice":105,"minecraft:stone_brick_slab":22,"minecraft:green_concrete":15,"minecraft:lever":1,"minecraft:red_sandstone":22,"minecraft:sea_lantern":5,"minecraft:black_concrete":147,"minecraft:diamond_shovel":34,"minecraft:quartz_pillar":368,"minecraft:daylight_detector":4,"minecraft:lime_banner":5,"minecraft:birch_fence_gate":31,"minecraft:black_stained_glass_pane":44,"minecraft:birch_slab":167,"minecraft:gray_stained_glass_pane":2,"minecraft:quartz_slab":66,"minecraft:heavy_weighted_pressure_plate":4,"minecraft:iron_block":3,"minecraft:grass_block":364,"minecraft:oak_stairs":6,"minecraft:acacia_slab":6,"minecraft:jungle_log":16,"minecraft:stone_button":46,"minecraft:quartz_block":29,"minecraft:sign":7,"minecraft:white_glazed_terracotta":2,"minecraft:jungle_stairs":1,"minecraft:stone_slab":595,"minecraft:red_terracotta":122,"minecraft:spruce_trapdoor":4,"minecraft:smooth_quartz":124,"minecraft:cut_red_sandstone":3,"minecraft:gravel":106,"minecraft:stone_bricks":93,"minecraft:bedrock":1,"minecraft:repeater":32,"minecraft:birch_button":10,"minecraft:birch_trapdoor":80,"minecraft:magma_block":2,"minecraft:glowstone":17,"minecraft:redstone_lamp":28,"minecraft:cobblestone":346,"minecraft:dark_oak_boat":1,"minecraft:iron_trapdoor":67,"minecraft:white_stained_glass_pane":12,"minecraft:white_stained_glass":7,"minecraft:andesite":112,"minecraft:grass_path":1,"minecraft:ice":54,"minecraft:stripped_oak_log":11,"minecraft:white_concrete":628,"minecraft:coarse_dirt":9,"minecraft:orange_stained_glass_pane":27,"minecraft:observer":7,"minecraft:orange_terracotta":13,"minecraft:smooth_stone":99,"minecraft:birch_stairs":240,"minecraft:experience_bottle":294},"minecraft:custom":{"minecraft:inspect_dropper":24,"minecraft:inspect_hopper":3,"minecraft:interact_with_crafting_table":1,"minecraft:play_one_minute":594660,"minecraft:open_shulker_box":9,"minecraft:leave_game":8,"minecraft:time_since_death":285296,"minecraft:time_since_rest":285323,"minecraft:sprint_one_cm":155473,"minecraft:damage_taken":810,"minecraft:walk_one_cm":215893,"minecraft:drop":23,"minecraft:damage_dealt":126,"minecraft:fly_one_cm":4583030,"minecraft:crouch_one_cm":90296,"minecraft:deaths":2,"minecraft:sneak_time":66341,"minecraft:walk_under_water_one_cm":4470,"minecraft:boat_one_cm":49377,"minecraft:aviate_one_cm":10185,"minecraft:jump":1025,"minecraft:walk_on_water_one_cm":3096,"minecraft:fall_one_cm":8776,"minecraft:inspect_dispenser":35},"minecraft:picked_up":{"minecraft:repeater":3,"minecraft:birch_planks":1,"minecraft:conduit":64,"minecraft:dirt":4,"minecraft:redstone_torch":2,"minecraft:quartz_stairs":1,"minecraft:iron_sword":3,"minecraft:stick":2,"minecraft:torch":6,"minecraft:birch_stairs":1,"minecraft:stone_button":4,"minecraft:quartz_pillar":1,"minecraft:redstone":16,"minecraft:spruce_door":1,"minecraft:firework_rocket":1137,"minecraft:cooked_cod":1,"minecraft:diamond":2,"minecraft:end_rod":1}},"DataVersion":1631}