{"stats":{"minecraft:picked_up":{"minecraft:diamond_sword":1,"minecraft:item_frame":1,"minecraft:blue_orchid":2,"minecraft:player_head":1740,"minecraft:poppy":1,"minecraft:birch_sapling":2,"minecraft:stick":31,"minecraft:torch":1,"minecraft:fire_charge":138,"minecraft:command_block":68,"minecraft:red_tulip":4,"minecraft:barrier":64,"minecraft:leather_chestplate":1,"minecraft:lilac":4,"minecraft:dark_oak_button":2,"minecraft:filled_map":1,"minecraft:name_tag":1,"minecraft:spawner":65,"minecraft:gray_carpet":1,"minecraft:wheat_seeds":3,"minecraft:cooked_porkchop":17,"minecraft:dragon_egg":64,"minecraft:lever":18,"minecraft:spruce_button":1,"minecraft:oak_sapling":1},"minecraft:mined":{"minecraft:cyan_bed":1},"minecraft:killed":{"minecraft:pig":1},"minecraft:dropped":{"minecraft:lilac":2,"minecraft:barrier":64,"minecraft:command_block":4,"minecraft:fire_charge":139,"minecraft:player_head":884,"minecraft:name_tag":1,"minecraft:diamond_sword":1,"minecraft:leather_chestplate":1,"minecraft:dragon_egg":64,"minecraft:stone_bricks":1,"minecraft:splash_potion":1},"minecraft:custom":{"minecraft:inspect_dropper":2,"minecraft:mob_kills":5,"minecraft:animals_bred":1,"minecraft:inspect_hopper":5,"minecraft:interact_with_crafting_table":1,"minecraft:open_shulker_box":3,"minecraft:leave_game":48,"minecraft:time_since_death":52925,"minecraft:climb_one_cm":596,"minecraft:sprint_one_cm":204378,"minecraft:walk_one_cm":554820,"minecraft:drop":32,"minecraft:deaths":6,"minecraft:sneak_time":98958,"minecraft:walk_under_water_one_cm":43121,"minecraft:jump":2745,"minecraft:walk_on_water_one_cm":3828,"minecraft:play_record":2,"minecraft:tune_noteblock":1,"minecraft:play_one_minute":1970754,"minecraft:pot_flower":3,"minecraft:sleep_in_bed":1,"minecraft:time_since_rest":52950,"minecraft:damage_taken":2400,"minecraft:damage_dealt":390,"minecraft:minecart_one_cm":5053,"minecraft:interact_with_beacon":4,"minecraft:swim_one_cm":28550,"minecraft:fly_one_cm":24986708,"minecraft:open_chest":26,"minecraft:crouch_one_cm":44714,"minecraft:aviate_one_cm":5900603,"minecraft:fall_one_cm":27053,"minecraft:inspect_dispenser":10},"minecraft:used":{"minecraft:oak_trapdoor":6,"minecraft:nether_brick_fence":46,"minecraft:jungle_leaves":113,"minecraft:blue_terracotta":13,"minecraft:iron_bars":78,"minecraft:white_tulip":2,"minecraft:light_gray_stained_glass_pane":554,"minecraft:dispenser":12,"minecraft:dead_tube_coral_fan":2,"minecraft:armor_stand":3,"minecraft:red_sandstone_slab":1,"minecraft:spruce_slab":306,"minecraft:redstone":4,"minecraft:poppy":7,"minecraft:bone_block":370,"minecraft:light_gray_carpet":34,"minecraft:light_blue_terracotta":8,"minecraft:spruce_planks":36,"minecraft:chest":14,"minecraft:white_terracotta":6,"minecraft:stone":680,"minecraft:stripped_jungle_wood":13,"minecraft:stripped_birch_wood":126,"minecraft:quartz_stairs":1260,"minecraft:grass":4,"minecraft:player_head":76,"minecraft:spruce_leaves":4,"minecraft:green_glazed_terracotta":1,"minecraft:torch":25,"minecraft:dragon_egg":5,"minecraft:dirt":13,"minecraft:anvil":112,"minecraft:white_carpet":18,"minecraft:hopper":87,"minecraft:brick_slab":248,"minecraft:prismarine_bricks":18,"minecraft:spruce_stairs":288,"minecraft:nether_bricks":359,"minecraft:prismarine_brick_stairs":8,"minecraft:cobblestone_wall":237,"minecraft:allium":3,"minecraft:orange_wool":228,"minecraft:nether_brick_slab":397,"minecraft:oak_wood":233,"minecraft:jungle_trapdoor":142,"minecraft:spruce_fence":73,"minecraft:cyan_wool":165,"minecraft:granite":49,"minecraft:light_blue_stained_glass":1,"minecraft:azure_bluet":8,"minecraft:nether_brick_stairs":5,"minecraft:milk_bucket":2,"minecraft:polished_diorite":320,"minecraft:fern":10,"minecraft:red_sandstone_stairs":1,"minecraft:stone_brick_slab":901,"minecraft:dark_oak_planks":241,"minecraft:sea_lantern":193,"minecraft:cyan_terracotta":533,"minecraft:stripped_dark_oak_wood":48,"minecraft:bricks":256,"minecraft:light_gray_stained_glass":179,"minecraft:red_tulip":7,"minecraft:quartz_pillar":324,"minecraft:quartz_slab":1059,"minecraft:jungle_fence_gate":11,"minecraft:red_wool":51,"minecraft:spruce_wood":97,"minecraft:grass_block":842,"minecraft:oak_stairs":17,"minecraft:blue_orchid":10,"minecraft:brick_stairs":107,"minecraft:spruce_button":4,"minecraft:smooth_sandstone":974,"minecraft:quartz_block":51,"minecraft:spawner":1,"minecraft:jungle_log":7,"minecraft:music_disc_chirp":2,"minecraft:dark_oak_leaves":4,"minecraft:dark_oak_slab":923,"minecraft:smooth_quartz":919,"minecraft:dark_oak_button":10,"minecraft:stone_brick_stairs":1389,"minecraft:stone_bricks":1150,"minecraft:item_frame":4,"minecraft:light_gray_wool":67,"minecraft:birch_button":40,"minecraft:tripwire_hook":5,"minecraft:birch_trapdoor":24,"minecraft:redstone_lamp":56,"minecraft:brown_carpet":15,"minecraft:magenta_wool":1443,"minecraft:gray_glazed_terracotta":3,"minecraft:iron_trapdoor":47,"minecraft:dark_oak_pressure_plate":2,"minecraft:white_stained_glass_pane":323,"minecraft:acacia_wood":28,"minecraft:gold_block":218,"minecraft:dragon_head":5,"minecraft:orange_terracotta":3,"minecraft:dark_prismarine_stairs":110,"minecraft:large_fern":2,"minecraft:stripped_spruce_wood":4,"minecraft:dark_oak_stairs":407,"minecraft:diorite":50,"minecraft:end_rod":64,"minecraft:pink_tulip":2,"minecraft:end_stone_bricks":92,"minecraft:iron_ore":10,"minecraft:cobblestone_stairs":658,"minecraft:sandstone_stairs":487,"minecraft:snow_block":68,"minecraft:prismarine_brick_slab":21,"minecraft:birch_planks":207,"minecraft:gray_carpet":12,"minecraft:polished_andesite":1403,"minecraft:prismarine":17,"minecraft:acacia_trapdoor":35,"minecraft:red_nether_bricks":315,"minecraft:lime_wool":1028,"minecraft:oak_planks":2,"minecraft:orange_tulip":1,"minecraft:sandstone":75,"minecraft:cut_sandstone":432,"minecraft:cauldron":14,"minecraft:clay":41,"minecraft:beacon":35,"minecraft:spruce_fence_gate":62,"minecraft:cobblestone_slab":37,"minecraft:gold_ore":12,"minecraft:oak_leaves":600,"minecraft:white_wool":34,"minecraft:dark_oak_trapdoor":120,"minecraft:rail":10,"minecraft:sand":2,"minecraft:lime_terracotta":159,"minecraft:terracotta":50,"minecraft:dark_prismarine_slab":145,"minecraft:crafting_table":8,"minecraft:light_blue_wool":52,"minecraft:sponge":2,"minecraft:yellow_concrete":2,"minecraft:acacia_leaves":18,"minecraft:dark_oak_fence_gate":7,"minecraft:dead_bubble_coral":1,"minecraft:chiseled_quartz_block":99,"minecraft:purple_terracotta":17,"minecraft:note_block":25,"minecraft:gray_concrete":97,"minecraft:painting":3,"minecraft:spruce_log":102,"minecraft:dark_oak_door":4,"minecraft:cyan_stained_glass":187,"minecraft:creeper_spawn_egg":2,"minecraft:birch_fence":15,"minecraft:redstone_torch":5,"minecraft:oak_log":272,"minecraft:gray_terracotta":86,"minecraft:piston":6,"minecraft:dark_prismarine":182,"minecraft:lever":29,"minecraft:flower_pot":4,"minecraft:oxeye_daisy":2,"minecraft:firework_rocket":7,"minecraft:chiseled_sandstone":123,"minecraft:birch_fence_gate":8,"minecraft:dark_oak_log":52,"minecraft:gray_stained_glass_pane":6,"minecraft:birch_slab":323,"minecraft:light_gray_concrete":122,"minecraft:cyan_bed":2,"minecraft:brown_wool":5,"minecraft:barrier":24,"minecraft:stone_button":22,"minecraft:cyan_carpet":24,"minecraft:spruce_pressure_plate":4,"minecraft:sign":10,"minecraft:jungle_stairs":5,"minecraft:cyan_concrete":145,"minecraft:stone_slab":60,"minecraft:red_terracotta":23,"minecraft:spruce_trapdoor":192,"minecraft:yellow_wool":1556,"minecraft:chiseled_stone_bricks":168,"minecraft:nether_wart_block":580,"minecraft:diamond_sword":1,"minecraft:coal_block":5,"minecraft:cobblestone":64,"minecraft:potion":12,"minecraft:cyan_stained_glass_pane":159,"minecraft:stripped_oak_wood":11,"minecraft:dark_oak_fence":30,"minecraft:white_stained_glass":29,"minecraft:andesite":915,"minecraft:sandstone_slab":145,"minecraft:grass_path":2,"minecraft:mossy_cobblestone_wall":1,"minecraft:sea_pickle":2,"minecraft:white_concrete":147,"minecraft:coarse_dirt":2,"minecraft:splash_potion":5,"minecraft:brown_mushroom_block":3,"minecraft:smooth_stone":286,"minecraft:purple_wool":311,"minecraft:birch_stairs":248,"minecraft:gray_stained_glass":228}},"DataVersion":1631}