{"stats":{"minecraft:used":{"minecraft:redstone_torch":22,"minecraft:glass":8,"minecraft:acacia_boat":1,"minecraft:end_rod":39,"minecraft:sea_lantern":5,"minecraft:ladder":1,"minecraft:barrier":50,"minecraft:stone_button":3,"minecraft:oak_planks":1,"minecraft:light_gray_carpet":5,"minecraft:music_disc_chirp":1,"minecraft:sign":4,"minecraft:chest":2,"minecraft:birch_boat":9,"minecraft:stone":79,"minecraft:quartz_stairs":4,"minecraft:stone_bricks":2,"minecraft:green_carpet":4,"minecraft:ocelot_spawn_egg":1,"minecraft:torch":9,"minecraft:diamond_sword":15,"minecraft:anvil":1,"minecraft:dirt":1,"minecraft:cobblestone":4,"minecraft:potion":1,"minecraft:polar_bear_spawn_egg":1,"minecraft:squid_spawn_egg":8},"minecraft:picked_up":{"minecraft:stick":1,"minecraft:torch":1,"minecraft:potion":1,"minecraft:ink_sac":8,"minecraft:firework_rocket":1,"minecraft:redstone_torch":4,"minecraft:music_disc_chirp":1},"minecraft:dropped":{"minecraft:firework_rocket":3},"minecraft:killed":{"minecraft:squid":8,"minecraft:ocelot":1},"minecraft:custom":{"minecraft:time_since_rest":5596,"minecraft:sprint_one_cm":129782,"minecraft:open_enderchest":5,"minecraft:damage_taken":680,"minecraft:walk_one_cm":302020,"minecraft:mob_kills":9,"minecraft:drop":3,"minecraft:inspect_hopper":4,"minecraft:damage_dealt":740,"minecraft:play_record":1,"minecraft:fly_one_cm":2354712,"minecraft:open_chest":8,"minecraft:crouch_one_cm":91566,"minecraft:play_one_minute":186000,"minecraft:deaths":4,"minecraft:sneak_time":9730,"minecraft:walk_under_water_one_cm":7980,"minecraft:boat_one_cm":9858,"minecraft:aviate_one_cm":454543,"minecraft:jump":1221,"minecraft:walk_on_water_one_cm":1537,"minecraft:time_since_death":5563,"minecraft:climb_one_cm":4027}},"DataVersion":1631}